django_hreflang-1.7.dist-info/DESCRIPTION.rst
django_hreflang-1.7.dist-info/METADATA
django_hreflang-1.7.dist-info/RECORD
django_hreflang-1.7.dist-info/WHEEL
django_hreflang-1.7.dist-info/metadata.json
django_hreflang-1.7.dist-info/top_level.txt
hreflang/__init__.py
hreflang/functions.py
hreflang/header.py
hreflang/templatetags/__init__.py
hreflang/templatetags/hreflang.py
