Metadata-Version: 2.0
Name: django-hreflang
Version: 1.7
Summary: Generate the hreflang html header lines when using i18n urls on Django sites
Home-page: https://bitbucket.org/mverleg/django_hreflang
Author: (the author)
Author-email: mdilligaf@gmail.com
License: Revised BSD License (LICENSE.txt)
Keywords: django,hreflang,http-headers,internationalization
Platform: UNKNOWN
Classifier: Development Status :: 5 - Production/Stable
Classifier: Intended Audience :: Developers
Classifier: Natural Language :: English
Classifier: License :: OSI Approved :: BSD License
Classifier: Operating System :: OS Independent
Classifier: Programming Language :: Python
Classifier: Programming Language :: Python :: 2
Classifier: Programming Language :: Python :: 2.6
Classifier: Programming Language :: Python :: 2.7
Classifier: Programming Language :: Python :: 3
Classifier: Programming Language :: Python :: 3.3
Classifier: Programming Language :: Python :: 3.4
Classifier: Programming Language :: Python :: 3.5
Classifier: Programming Language :: Python :: Implementation :: PyPy
Classifier: Topic :: Software Development :: Libraries :: Python Modules
Requires-Dist: django
